cascades/__init__.py
cascades/_src/__init__.py
cascades/_src/handlers.py
cascades/_src/handlers_test.py
cascades/_src/sampler.py
cascades/_src/sampler_test.py
cascades/_src/distributions/__init__.py
cascades/_src/distributions/base.py
cascades/_src/distributions/choose.py
cascades/_src/distributions/gpt.py
cascades/_src/distributions/strings.py
cascades/_src/distributions/strings_test.py
cascades/_src/inference/__init__.py
cascades/_src/inference/base.py
cascades/_src/inference/rejection_sampling.py
cascades/_src/inference/rejection_sampling_test.py
cascades/examples/calculator.py
cascades/examples/scratchpad.py
cascades/examples/scratchpad_test.py
cascades/examples/tasks/gsm8k.py
cascades/examples/tasks/svamp.py
cascades-0.3.2.dist-info/LICENSE
cascades-0.3.2.dist-info/WHEEL
cascades-0.3.2.dist-info/METADATA
cascades-0.3.2.dist-info/RECORD
