Metadata-Version: 2.1
Name: cascades
Version: 0.3.2
Summary: 
Keywords: 
Author-email: Cascades authors <model-cascades@google.com>
Requires-Python: >=3.7
Classifier: Programming Language :: Python :: 3
Classifier: Programming Language :: Python :: 3 :: Only
Classifier: License :: OSI Approved :: Apache Software License
Classifier: Intended Audience :: Science/Research
Requires-Dist: jax[cpu]
Requires-Dist: numpyro
Requires-Dist: immutabledict
Requires-Dist: openai
Requires-Dist: pytest ; extra == "dev"
Requires-Dist: pytest-xdist ; extra == "dev"
Requires-Dist: pylint>=2.6.0 ; extra == "dev"
Requires-Dist: yapf ; extra == "dev"
Project-URL: homepage, https://github.com/google-research/cascades
Project-URL: repository, https://github.com/google-research/cascades
Provides-Extra: dev
